LICENSE
README.md
setup.cfg
setup.py
test/test_messages.py
toros/__init__.py
toros/logging.py
toros/messages.py
toros/tf2.py
toros/writer.py
toros.egg-info/PKG-INFO
toros.egg-info/SOURCES.txt
toros.egg-info/dependency_links.txt
toros.egg-info/requires.txt
toros.egg-info/top_level.txt